googleSearch/__init__.py
googleSearch/bot/__init__.py
googleSearch/models/__init__.py
googleSearch/models/email.py
googleSearch/models/site_rank.py
googleSearch/models/upload_data.py
googleSearch/parsers/__init__.py
googleSearch/parsers/googleList.py
googleSearch/parsers/list_detail.py
googleSearch/utils/__init__.py
googleSearch/utils/config.py
googleSearch/utils/logger.py
googleSearch/utils/settings.py
HjGoogleSearch-1.0.3.dist-info/LICENSE
HjGoogleSearch-1.0.3.dist-info/METADATA
HjGoogleSearch-1.0.3.dist-info/WHEEL
HjGoogleSearch-1.0.3.dist-info/top_level.txt
HjGoogleSearch-1.0.3.dist-info/RECORD
